neze_young_interference-1.dist-info/METADATA
neze_young_interference-1.dist-info/RECORD
neze_young_interference-1.dist-info/WHEEL
neze_young_interference-1.dist-info/top_level.txt
young/__init__.py
young/__main__.py
young/attenuation.py
young/config.py
young/demo.py
young/interference.py
young/tools.py
young/demos/__init__.py
young/demos/attenuation.py
young/demos/beforeafter.py
young/demos/movie.py
young/demos/pyplot.py
