Metadata-Version: 2.1
Name: neze-young-interference
Version: 1
Summary: Young interference visualisation
Home-page: UNKNOWN
Author: Clement Durand
Author-email: durand.clement.13@gmail.com
License: UNKNOWN
Platform: UNKNOWN
Classifier: Programming Language :: Python :: 3
Requires-Dist: matplotlib
Requires-Dist: numpy
Requires-Dist: python-dateutil
